streamlit_TTS/__init__.py
streamlit_TTS/frontend/build/asset-manifest.json
streamlit_TTS/frontend/build/bootstrap.min.css
streamlit_TTS/frontend/build/index.html
streamlit_TTS/frontend/build/static/css/main.31d6cfe0.css
streamlit_TTS/frontend/build/static/js/main.cb3dcb7d.js
streamlit_TTS/frontend/build/static/js/main.cb3dcb7d.js.LICENSE.txt
streamlit_TTS/frontend/build/static/js/main.cb3dcb7d.js.map
streamlit_TTS-0.0.6.dist-info/LICENSE
streamlit_TTS-0.0.6.dist-info/METADATA
streamlit_TTS-0.0.6.dist-info/WHEEL
streamlit_TTS-0.0.6.dist-info/top_level.txt
streamlit_TTS-0.0.6.dist-info/RECORD
