Metadata-Version: 2.1
Name: streamlit-TTS
Version: 0.0.6
Summary: Streamlit component providing tools to convert text to speech and play audio directly in the browser
Home-page: https://github.com/B4PT0R/streamlit-TTS
Author: Baptiste Ferrand
Author-email: bferrand.maths@gmail.com.com
Requires-Python: >=3.7
License-File: LICENSE
Requires-Dist: streamlit (>=0.63)
Requires-Dist: pydub
Requires-Dist: gtts
